path4gmns/__init__.py
path4gmns/accessibility.py
path4gmns/classes.py
path4gmns/colgen.py
path4gmns/consts.py
path4gmns/dtaapi.py
path4gmns/fw.py
path4gmns/io.py
path4gmns/odme.py
path4gmns/path.py
path4gmns/simulation.py
path4gmns/utils.py
path4gmns/zonesyn.py
path4gmns/bin/DTALite.dll
path4gmns/bin/DTALite.so
path4gmns/bin/DTALiteMM.dll
path4gmns/bin/DTALiteMM.so
path4gmns/bin/DTALiteMM_arm.dylib
path4gmns/bin/DTALiteMM_x86.dylib
path4gmns/bin/DTALite_arm.dylib
path4gmns/bin/DTALite_x86.dylib
path4gmns/bin/path_engine.dll
path4gmns/bin/path_engine.so
path4gmns/bin/path_engine_arm.dylib
path4gmns/bin/path_engine_x86.dylib
path4gmns-0.10.0.dist-info/licenses/LICENSE
path4gmns-0.10.0.dist-info/METADATA
path4gmns-0.10.0.dist-info/WHEEL
path4gmns-0.10.0.dist-info/top_level.txt
path4gmns-0.10.0.dist-info/RECORD
