Metadata-Version: 2.4
Name: path4gmns
Version: 0.10.0
Summary: An open-source, cross-platform, lightweight, and fast Python                path engine for networks encoded in GMNS
Home-page: https://github.com/jdlph/PATH4GMNS
Author: Dr. Xuesong Zhou, Dr. Peiheng Li
Author-email: xzhou74@asu.edu, jdlph@hotmail.com
License: Apache License 2.0
Classifier: Programming Language :: Python :: 3
Classifier: License :: OSI Approved :: Apache Software License
Classifier: Operating System :: OS Independent
License-File: LICENSE
Dynamic: author
Dynamic: author-email
Dynamic: classifier
Dynamic: description
Dynamic: description-content-type
Dynamic: home-page
Dynamic: license
Dynamic: license-file
Dynamic: summary
